.landscape.yml
.travis.yml
AUTHORS
ChangeLog
LICENSE
README.rst
requirements.txt
setup.cfg
setup.py
fixturebuilder/__init__.py
fixturebuilder/fixturebuilder.py
fixturebuilder/test_fixturebuilder.py
fixturebuilder_py.egg-info/PKG-INFO
fixturebuilder_py.egg-info/SOURCES.txt
fixturebuilder_py.egg-info/dependency_links.txt
fixturebuilder_py.egg-info/not-zip-safe
fixturebuilder_py.egg-info/pbr.json
fixturebuilder_py.egg-info/requires.txt
fixturebuilder_py.egg-info/top_level.txt
scripts/build
scripts/pypiPublish
scripts/reportCoverage
scripts/test